bibclean/__init__.py
bibclean/_exception.py
bibclean/_typing.py
bibclean/_version.py
bibclean/check.py
bibclean/clean.py
bibclean/io.py
bibclean/commands/__init__.py
bibclean/commands/bibclean.py
bibclean/commands/bibclean_check.py
bibclean/commands/sys_info.py
bibclean/config/__init__.py
bibclean/config/config.py
bibclean/config/default.toml
bibclean/utils/__init__.py
bibclean/utils/_checks.py
bibclean/utils/_docs.py
bibclean/utils/_fixes.py
bibclean/utils/_imports.py
bibclean/utils/config.py
bibclean/utils/logs.py
bibclean-0.8.0.dist-info/LICENSE
bibclean-0.8.0.dist-info/METADATA
bibclean-0.8.0.dist-info/WHEEL
bibclean-0.8.0.dist-info/entry_points.txt
bibclean-0.8.0.dist-info/top_level.txt
bibclean-0.8.0.dist-info/RECORD
