Metadata-Version: 2.1
Name: bibclean
Version: 0.8.0
Summary: A simple BibTex file checker and cleaner.
Author-email: Mathieu Scheltienne <mathieu.scheltienne@fcbg.ch>
Maintainer-email: Mathieu Scheltienne <mathieu.scheltienne@fcbg.ch>
License: MIT License
Project-URL: homepage, https://github.com/mscheltienne/bibclean
Project-URL: documentation, https://mscheltienne.github.io/bibclean/
Project-URL: source, https://github.com/mscheltienne/bibclean
Project-URL: tracker, https://github.com/mscheltienne/bibclean/issues
Keywords: bibliography,bibtex,python
Classifier: Intended Audience :: Developers
Classifier: License :: OSI Approved :: MIT License
Classifier: Natural Language :: English
Classifier: Operating System :: Microsoft :: Windows
Classifier: Operating System :: Unix
Classifier: Operating System :: MacOS
Classifier: Programming Language :: Python :: 3 :: Only
Classifier: Programming Language :: Python :: 3.9
Classifier: Programming Language :: Python :: 3.10
Classifier: Programming Language :: Python :: 3.11
Classifier: Programming Language :: Python :: 3.12
Requires-Python: >=3.9
License-File: LICENSE
Requires-Dist: bibtexparser ==1.4.0
Requires-Dist: numpy >=1.21
Requires-Dist: packaging
Requires-Dist: psutil
Requires-Dist: toml
Provides-Extra: all
Requires-Dist: bibclean[style] ; extra == 'all'
Requires-Dist: bibclean[doc] ; extra == 'all'
Requires-Dist: bibclean[test] ; extra == 'all'
Requires-Dist: bibclean[build] ; extra == 'all'
Provides-Extra: build
Requires-Dist: build ; extra == 'build'
Requires-Dist: twine ; extra == 'build'
Provides-Extra: doc
Requires-Dist: furo ; extra == 'doc'
Requires-Dist: numpydoc ; extra == 'doc'
Requires-Dist: sphinx ; extra == 'doc'
Requires-Dist: sphinx-copybutton ; extra == 'doc'
Requires-Dist: sphinx-design ; extra == 'doc'
Requires-Dist: sphinx-issues ; extra == 'doc'
Provides-Extra: full
Requires-Dist: bibclean[all] ; extra == 'full'
Provides-Extra: style
Requires-Dist: black ; extra == 'style'
Requires-Dist: codespell ; extra == 'style'
Requires-Dist: isort ; extra == 'style'
Requires-Dist: pydocstyle[toml] ; extra == 'style'
Requires-Dist: ruff ; extra == 'style'
Provides-Extra: test
Requires-Dist: pytest ; extra == 'test'
Requires-Dist: pytest-cov ; extra == 'test'
